typed_configparser/__init__.py
typed_configparser/casting.py
typed_configparser/errors.py
typed_configparser/loader.py
typed_configparser/py.typed
configparser_typed-0.1.0.dist-info/METADATA
configparser_typed-0.1.0.dist-info/WHEEL
configparser_typed-0.1.0.dist-info/top_level.txt
configparser_typed-0.1.0.dist-info/RECORD
