Metadata-Version: 2.4
Name: configparser-typed
Version: 0.1.0
Summary: A typed, validated wrapper around Python's built-in configparser
Author-email: Pierre <pierrebruno@hotmail.ch>
Maintainer-email: Pierre <pierrebruno@hotmail.ch>
License-Expression: MIT
Project-URL: Homepage, https://github.com/PierrunoYT/typed-configparser
Project-URL: Repository, https://github.com/PierrunoYT/typed-configparser
Project-URL: Issues, https://github.com/PierrunoYT/typed-configparser/issues
Project-URL: Changelog, https://github.com/PierrunoYT/typed-configparser/releases
Keywords: config,ini,configparser,typed,dataclass,pydantic,validation,configuration
Classifier: Development Status :: 3 - Alpha
Classifier: Intended Audience :: Developers
Classifier: Operating System :: OS Independent
Classifier: Programming Language :: Python :: 3
Classifier: Programming Language :: Python :: 3.10
Classifier: Programming Language :: Python :: 3.11
Classifier: Programming Language :: Python :: 3.12
Classifier: Programming Language :: Python :: 3.13
Classifier: Topic :: Software Development :: Libraries :: Python Modules
Classifier: Topic :: Utilities
Classifier: Typing :: Typed
Requires-Python: >=3.10
Provides-Extra: dev
Requires-Dist: pytest>=7.0; extra == "dev"
Requires-Dist: pytest-cov>=4.0; extra == "dev"
Requires-Dist: mypy>=1.0; extra == "dev"
Requires-Dist: ruff>=0.1.0; extra == "dev"
Provides-Extra: test
Requires-Dist: pytest>=7.0; extra == "test"
Requires-Dist: pytest-cov>=4.0; extra == "test"
